sagiri/__init__.py
sagiri-0.1.0.dist-info/WHEEL
sagiri-0.1.0.dist-info/METADATA
sagiri-0.1.0.dist-info/RECORD
